pyeventsystem/__init__.py
pyeventsystem/events.py
pyeventsystem/interfaces.py
pyeventsystem/middleware.py
tests/__init__.py
tests/test_event_system.py
tests/test_middleware_system.py
pyeventsystem-0.1.0.dist-info/LICENSE
pyeventsystem-0.1.0.dist-info/METADATA
pyeventsystem-0.1.0.dist-info/WHEEL
pyeventsystem-0.1.0.dist-info/top_level.txt
pyeventsystem-0.1.0.dist-info/RECORD
